HISTORY
pyapp/__init__.py
pyapp/app/__init__.py
pyapp/app/argument_actions.py
pyapp/app/argument_types.py
pyapp/app/arguments.py
pyapp/app/builtin_handlers.py
pyapp/app/init_logger.py
pyapp/app/logging_formatter.py
pyapp/checks/__init__.py
pyapp/checks/built_in.py
pyapp/checks/messages.py
pyapp/checks/registry.py
pyapp/checks/report.py
pyapp/compatability.py
pyapp/conf/__init__.py
pyapp/conf/base_settings.py
pyapp/conf/helpers/__init__.py
pyapp/conf/helpers/bases.py
pyapp/conf/helpers/plugins.py
pyapp/conf/helpers/providers.py
pyapp/conf/loaders/__init__.py
pyapp/conf/loaders/base.py
pyapp/conf/loaders/content_types.py
pyapp/conf/loaders/file_loader.py
pyapp/conf/loaders/http_loader.py
pyapp/conf/report.py
pyapp/documentation/__init__.py
pyapp/documentation/settings.py
pyapp/documentation/sphinx.py
pyapp/events.py
pyapp/exceptions.py
pyapp/extensions/__init__.py
pyapp/extensions/registry.py
pyapp/extensions/report.py
pyapp/feature_flags.py
pyapp/injection.py
pyapp/multiprocessing.py
pyapp/py.typed
pyapp/testing/__init__.py
pyapp/testing/pytest_plugin.py
pyapp/typed_settings.py
pyapp/utils/__init__.py
pyapp/utils/compatibility.py
pyapp/utils/inspect.py
pyapp/versioning.py
pyapp-4.16.1.dist-info/AUTHORS
pyapp-4.16.1.dist-info/LICENSE
pyapp-4.16.1.dist-info/METADATA
pyapp-4.16.1.dist-info/WHEEL
pyapp-4.16.1.dist-info/entry_points.txt
pyapp-4.16.1.dist-info/RECORD
