Metadata-Version: 2.1
Name: pyapp
Version: 4.16.1
Summary: A Python application framework - Let us handle the boring stuff!
Home-page: https://github.com/pyapp-org/pyapp
License: BSD-3-Clause
Keywords: framework,application
Author: Tim Savage
Author-email: tim@savage.company
Requires-Python: >=3.10,<4.0
Classifier: Development Status :: 5 - Production/Stable
Classifier: Intended Audience :: Developers
Classifier: License :: OSI Approved :: BSD License
Classifier: Operating System :: OS Independent
Classifier: Programming Language :: Python :: 3
Classifier: Programming Language :: Python :: 3.10
Classifier: Programming Language :: Python :: 3.11
Classifier: Programming Language :: Python :: 3.12
Classifier: Programming Language :: Python :: 3.13
Classifier: Programming Language :: Python :: Implementation :: CPython
Classifier: Programming Language :: Python :: Implementation :: PyPy
Classifier: Topic :: Software Development :: Libraries :: Application Frameworks
Classifier: Topic :: Software Development :: Libraries :: Python Modules
Provides-Extra: toml
Provides-Extra: yaml
Requires-Dist: argcomplete (>=3.2,<4.0)
Requires-Dist: colorama
Requires-Dist: importlib_metadata ; python_full_version <= "3.9.0"
Requires-Dist: pyyaml ; extra == "yaml"
Requires-Dist: toml ; extra == "toml"
Requires-Dist: typing_extensions
Requires-Dist: yarl
Project-URL: Bug Tracker, https://github.com/pyapp-org/pyapp/issues
Project-URL: Documentation, https://docs.pyapp.info
Project-URL: Repository, https://github.com/pyapp-org/pyapp
